hahusms/__init__.py
hahusms/sms.py
hahusms-0.0.1.dist-info/LICENSE
hahusms-0.0.1.dist-info/METADATA
hahusms-0.0.1.dist-info/WHEEL
hahusms-0.0.1.dist-info/top_level.txt
hahusms-0.0.1.dist-info/RECORD
