Metadata-Version: 2.1
Name: hahusms
Version: 0.0.1
Summary: A simple python package to send SMS via HahuCloud API
Home-page: https://github.com/chapimenge3/hahusms/
Author: Chapi Menge
Author-email: chapimenge3@gmail.com
License: UNKNOWN
Project-URL: Bug Tracker, https://github.com/chapimenge3/hahusms/issues
Platform: UNKNOWN
Classifier: Programming Language :: Python :: 3
Classifier: License :: OSI Approved :: MIT License
Classifier: Operating System :: OS Independent
Requires-Python: >=3.7
License-File: LICENSE
Requires-Dist: requests
